{
    "faturamento": [
        {"dia": 1, "valor": 22174.66},
        {"dia": 2, "valor": 24512.07},
        {"dia": 3, "valor": 0.0},
        {"dia": 4, "valor": 17895.60},
        {"dia": 5, "valor": 21234.55},
        {"dia": 6, "valor": 0.0},
        {"dia": 7, "valor": 0.0},
        {"dia": 8, "valor": 18423.58},
        {"dia": 9, "valor": 20234.50},
        {"dia": 10, "valor": 23657.42},
        {"dia": 11, "valor": 0.0},
        {"dia": 12, "valor": 0.0},
        {"dia": 13, "valor": 19223.45},
        {"dia": 14, "valor": 22345.67},
        {"dia": 15, "valor": 0.0},
        {"dia": 16, "valor": 0.0},
        {"dia": 17, "valor": 20123.40},
        {"dia": 18, "valor": 24567.89},
        {"dia": 19, "valor": 0.0},
        {"dia": 20, "valor": 0.0},
        {"dia": 21, "valor": 21234.56},
        {"dia": 22, "valor": 23456.78},
        {"dia": 23, "valor": 0.0},
        {"dia": 24, "valor": 0.0},
        {"dia": 25, "valor": 19234.50},
        {"dia": 26, "valor": 22345.60},
        {"dia": 27, "valor": 0.0},
        {"dia": 28, "valor": 0.0},
        {"dia": 29, "valor": 20123.45},
        {"dia": 30, "valor": 24567.89}
    ]
}